pyDRMetrics/__init__.py
pyDRMetrics/calculate_recon_error.py
pyDRMetrics/coranking_matrix.py
pyDRMetrics/dr.py
pyDRMetrics/drx.py
pyDRMetrics/plt2base64.py
pyDRMetrics/pyDRMetrics.py
pyDRMetrics/visualize_matrix.py
pyDRMetrics/visualize_sample_reconstruction.py
pyDRMetrics-0.0.7.dist-info/LICENSE
pyDRMetrics-0.0.7.dist-info/METADATA
pyDRMetrics-0.0.7.dist-info/WHEEL
pyDRMetrics-0.0.7.dist-info/licence.txt
pyDRMetrics-0.0.7.dist-info/top_level.txt
pyDRMetrics-0.0.7.dist-info/RECORD
