Metadata-Version: 2.1
Name: pyDRMetrics
Version: 0.0.7
Summary: A Python toolkit for dimensionality reduction quality assessment
Home-page: https://github.com/zhangys11/pyDRMetrics
Author: Yinsheng Zhang (Ph.D.)
Author-email: oo@zju.edu.cn
Project-URL: Bug Tracker, https://github.com/zhangys11/pyDRMetrics/issues
Classifier: Programming Language :: Python :: 3
Classifier: License :: OSI Approved :: GNU Lesser General Public License v3 or later (LGPLv3+)
Classifier: Operating System :: OS Independent
Classifier: Topic :: Scientific/Engineering :: Mathematics
Requires-Python: >=3.6
License-File: LICENSE
License-File: licence.txt
